cdmb/CommonDataModel.py
cdmb/__init__.py
cdmb/cohort/Cohort.py
cdmb/cohort/Crosswalks.py
cdmb/cohort/__init__.py
cdmb/entities/Catalog.py
cdmb/entities/Entity.py
cdmb/entities/Rule.py
cdmb/entities/RuleSet.py
cdmb/entities/Variable.py
cdmb/entities/__init__.py
cdmb/project/Author.py
cdmb/project/Metadata.py
cdmb/project/__init__.py
cdmb/relationships/Relationship.py
cdmb/relationships/__init__.py
cdmb/templates/Utils.py
cdmb/templates/__init__.py
cdmb/templates/files/.gitignore
cdmb/templates/files/LICENSE.md
cdmb/templates/files/README.md
cdmb/templates/files/_quarto.yml
cdmb/templates/files/check_load.py
cdmb/templates/files/dqa.py
cdmb/templates/files/man_container_deployment.md
cdmb/templates/files/r_report_template.qmd
cdmb/templates/files/readme_input.txt
cdmb/templates/files/readme_logs.txt
cdmb/templates/files/readme_outputs.txt
cdmb/templates/files/testing.py
cdmb/templates/files/validator.py
cdmb/templates/files/validator_report.qmd
cdmb/typing/CommonDataModelTyping.py
cdmb/typing/__init__.py
cdmb/ui/UILauncher.py
cdmb/ui/__init__.py
cdmb/ui/static_ui/_app/env.js
cdmb/ui/static_ui/_app/immutable/assets/0.Bw2xbFvd.css
cdmb/ui/static_ui/_app/immutable/assets/2.LU0zgPFt.css
cdmb/ui/static_ui/_app/immutable/assets/4.KmaTEWjv.css
cdmb/ui/static_ui/_app/immutable/assets/6.CxVi64r8.css
cdmb/ui/static_ui/_app/immutable/assets/_layout.ClX2pZcp.css
cdmb/ui/static_ui/_app/immutable/assets/_page.CxVi64r8.css
cdmb/ui/static_ui/_app/immutable/assets/_page.KmaTEWjv.css
cdmb/ui/static_ui/_app/immutable/assets/_page.LU0zgPFt.css
cdmb/ui/static_ui/_app/immutable/assets/eu_flag.BmL3JA3h.jpg
cdmb/ui/static_ui/_app/immutable/assets/favicon.Dm81UgH5.png
cdmb/ui/static_ui/_app/immutable/assets/fira-mono-cyrillic-400-normal.36-45Uyg.woff2
cdmb/ui/static_ui/_app/immutable/assets/fira-mono-cyrillic-400-normal.Dq7SlH2J.woff
cdmb/ui/static_ui/_app/immutable/assets/fira-mono-cyrillic-ext-400-normal.0xXfcOOq.woff
cdmb-1.3.7.dist-info/LICENSE
cdmb-1.3.7.dist-info/METADATA
cdmb-1.3.7.dist-info/WHEEL
cdmb-1.3.7.dist-info/RECORD
