Metadata-Version: 2.1
Name: cdmb
Version: 1.3.7
Summary: Common Data Model Builder library
Home-page: https://github.com/cienciadedatosysalud/cdmb
License: CC-BY-NC-4.0
Keywords: common data model,real-world data,health data,synthetic data,secondary use,health,healthcare
Author: Javier González-Galindo
Author-email: jgonzalezga.iacs@aragon.es
Maintainer: Javier González-Galindo
Maintainer-email: jgonzalezga.iacs@aragon.es
Requires-Python: >=3.9,<=3.12.5
Classifier: Development Status :: 3 - Alpha
Classifier: Intended Audience :: Healthcare Industry
Classifier: Intended Audience :: Science/Research
Classifier: License :: Other/Proprietary License
Classifier: Programming Language :: Python :: 3
Classifier: Programming Language :: Python :: 3.9
Classifier: Programming Language :: Python :: 3.10
Classifier: Programming Language :: Python :: 3.11
Classifier: Programming Language :: Python :: Implementation
Classifier: Topic :: Scientific/Engineering :: Bio-Informatics
Classifier: Topic :: Scientific/Engineering :: Human Machine Interfaces
Classifier: Topic :: Software Development :: Libraries :: Python Modules
Requires-Dist: chardet (==5.2.0)
Requires-Dist: duckdb (==1.0.0)
Requires-Dist: faker (==28.0.0)
Requires-Dist: fastapi (==0.112.2)
Requires-Dist: graphviz (==0.20.3)
Requires-Dist: openpyxl (==3.1.5)
Requires-Dist: pandas (==2.2.2)
Requires-Dist: poetry-semver (==0.1.0)
Requires-Dist: pytest (==8.3.2)
Requires-Dist: python-multipart (==0.0.9)
Requires-Dist: rocrate (==0.10.0)
Requires-Dist: uvicorn (==0.30.6)
Project-URL: Repository, https://github.com/cienciadedatosysalud/cdmb
